anonymizer/__init__.py
anonymizer/anonymizer.py
tdf.labnum.anonymizer-0.2.dist-info/METADATA
tdf.labnum.anonymizer-0.2.dist-info/WHEEL
tdf.labnum.anonymizer-0.2.dist-info/top_level.txt
tdf.labnum.anonymizer-0.2.dist-info/RECORD
