Metadata-Version: 2.1
Name: tdf.labnum.anonymizer
Version: 0.2
Requires-Dist: nltk
Requires-Dist: pydantic
Requires-Dist: faker
Requires-Dist: pandas
